servicenow_exporter/__init__.py
servicenow_exporter/main.py
servicenow_bulk-0.0.1.dist-info/METADATA
servicenow_bulk-0.0.1.dist-info/WHEEL
servicenow_bulk-0.0.1.dist-info/entry_points.txt
servicenow_bulk-0.0.1.dist-info/top_level.txt
servicenow_bulk-0.0.1.dist-info/RECORD
