Metadata-Version: 2.4
Name: servicenow-bulk
Version: 0.0.1
Summary: An MCP server for exporting large datasets from ServiceNow.
Author-email: veera reddy <mallikarjun.servicenow@gmail.com>
Requires-Python: >=3.12
Requires-Dist: httpx>=0.28.1
Requires-Dist: mcp[cli]>=1.12.3
